qtility/__init__.py
qtility/six/__init__.py
qtility/six/app.py
qtility/six/derive.py
qtility/six/designer.py
qtility/six/layouts.py
qtility/six/menus.py
qtility/six/pixmaps.py
qtility/six/request.py
qtility/six/sizing.py
qtility/six/styling.py
qtility/six/widgets.py
qtility/six/windows.py
qtility/two/__init__.py
qtility/two/app.py
qtility/two/derive.py
qtility/two/designer.py
qtility/two/layouts.py
qtility/two/menus.py
qtility/two/pixmaps.py
qtility/two/request.py
qtility/two/sizing.py
qtility/two/styling.py
qtility/two/widgets.py
qtility/two/windows.py
qtility-1.0.7.dist-info/licenses/LICENSE
qtility-1.0.7.dist-info/METADATA
qtility-1.0.7.dist-info/WHEEL
qtility-1.0.7.dist-info/top_level.txt
qtility-1.0.7.dist-info/RECORD
