Metadata-Version: 2.4
Name: qtility
Version: 1.0.7
Summary: Support functions for working with PySide2/PySide6
Home-page: https://github.com/mikemalinowski/qtility
Author: Mike Malinowski
Author-email: mike.malinowski@outlook.com
Keywords: pyside pyside2 pyside6 pyqt4 pyqt5 malinowski
Classifier: Programming Language :: Python
Classifier: License :: OSI Approved :: MIT License
Classifier: Operating System :: OS Independent
Requires-Python: >3.5.2
License-File: LICENSE
Requires-Dist: scribble
Requires-Dist: qt.py
Dynamic: author
Dynamic: author-email
Dynamic: classifier
Dynamic: description
Dynamic: description-content-type
Dynamic: home-page
Dynamic: keywords
Dynamic: license-file
Dynamic: requires-dist
Dynamic: requires-python
Dynamic: summary
